hitchdb/__init__.py
hitchdb/db.py
hitchdb/fixture.py
hitchdb/tbls.py
hitchdb/utils.py
hitchdb-0.1.4.dist-info/LICENSE.txt
hitchdb-0.1.4.dist-info/METADATA
hitchdb-0.1.4.dist-info/WHEEL
hitchdb-0.1.4.dist-info/top_level.txt
hitchdb-0.1.4.dist-info/RECORD
