Metadata-Version: 2.1
Name: hitchdb
Version: 0.1.4
Summary: StrictYAML database fixtures with tbls.
Author-email: Colm O'Connor <colm.oconnor.github@gmail.com>
License: Elastic License 2.0
Project-URL: homepage, https://hitchdev.com/hitchdb
Project-URL: documentation, https://hitchdev.com/hitchdb/using
Project-URL: repository, https://github.com/hitchdev/hitchdb
Project-URL: changelog, https://hitchdev.com/hitchdb/changelog
Keywords: yaml,hitchdev,bdd,tdd,database,fixtures
Classifier: Programming Language :: Python :: 3
Classifier: Topic :: Software Development :: Quality Assurance
Classifier: Topic :: Software Development :: Testing
Classifier: Topic :: Text Processing :: Markup
Classifier: Topic :: Software Development :: Libraries
Classifier: Natural Language :: English
Classifier: Environment :: Console
Requires-Python: >=3.7.0
License-File: LICENSE.txt
Requires-Dist: strictyaml >=1.4.3
Requires-Dist: python-slugify >=1.2.1
